MANIFEST.in
README.md
setup.py
ing_theme_matplotlib/__init__.py
ing_theme_matplotlib/mpl_style.py
ing_theme_matplotlib.egg-info/PKG-INFO
ing_theme_matplotlib.egg-info/SOURCES.txt
ing_theme_matplotlib.egg-info/dependency_links.txt
ing_theme_matplotlib.egg-info/requires.txt
ing_theme_matplotlib.egg-info/top_level.txt
ing_theme_matplotlib/logos/ING_Logo.png
ing_theme_matplotlib/logos/RPAA_Logo_RGB_Line.png
ing_theme_matplotlib/logos/RPAA_Logo_RGB_Line_Dark.png
ing_theme_matplotlib/styles/common.mplstyle
ing_theme_matplotlib/styles/dark.mplstyle
ing_theme_matplotlib/styles/light.mplstyle