Metadata-Version: 2.1
Name: ing-theme-matplotlib
Version: 0.1.4
Summary: ING styles for common plotting libraries
Home-page: https://gitlab.com/ing_rpaa/ing_theme_matplotlib
Author: Ahmet Emre Bayraktar - ING
Author-email: aemrebayraktar@gmail.com
License: Apache 2.0
Platform: UNKNOWN
Classifier: Programming Language :: Python :: 3
Classifier: License :: OSI Approved :: Apache Software License
Classifier: Operating System :: OS Independent
Requires-Python: >=3.5
